micropack/BUILD
micropack/__init__.py
micropack/buffer.py
micropack/io.py
micropack/protocol.py
micropack-0.1.0.dist-info/LICENSE
micropack-0.1.0.dist-info/WHEEL
micropack-0.1.0.dist-info/METADATA
micropack-0.1.0.dist-info/RECORD
