Metadata-Version: 2.1
Name: micropack
Version: 0.1.0
Summary: Lightweight JSON serialisation and diff-patching tool for bandwitdth constained applications
License: MIT
Author: Bernard Greyling
Author-email: bpgreyling@gmail.com
Requires-Python: >=3.8,<4.0
Classifier: License :: OSI Approved :: MIT License
Classifier: Programming Language :: Python :: 3
Classifier: Programming Language :: Python :: 3.8
Classifier: Programming Language :: Python :: 3.9
Classifier: Programming Language :: Python :: 3.10
Classifier: Programming Language :: Python :: 3.11
